jyablonski_common_modules/__init__.py
jyablonski_common_modules/aws/__init__.py
jyablonski_common_modules/aws/exceptions.py
jyablonski_common_modules/aws/secrets_manager.py
jyablonski_common_modules/aws/ssm.py
jyablonski_common_modules/aws/s3/__init__.py
jyablonski_common_modules/aws/s3/core.py
jyablonski_common_modules/aws/s3/parquet.py
jyablonski_common_modules/general/__init__.py
jyablonski_common_modules/general/core.py
jyablonski_common_modules/general/date_partitioning.py
jyablonski_common_modules/general/feature_flags.py
jyablonski_common_modules/general/slack.py
jyablonski_common_modules/logging/__init__.py
jyablonski_common_modules/logging/base_logger.py
jyablonski_common_modules/logging/os_logger.py
jyablonski_common_modules/sql/__init__.py
jyablonski_common_modules/sql/connection.py
jyablonski_common_modules/sql/writers.py
jyablonski_common_modules-0.0.11.dist-info/METADATA
jyablonski_common_modules-0.0.11.dist-info/WHEEL
jyablonski_common_modules-0.0.11.dist-info/RECORD
