Metadata-Version: 2.4
Name: jyablonski_common_modules
Version: 0.0.11
Author-email: jyablonski9 <jyablonski9@gmail.com>
Maintainer-email: jyablonski9 <jyablonski9@gmail.com>
Keywords: helper functions,personal
Classifier: Topic :: Software Development :: Build Tools
Classifier: Topic :: Software Development :: Libraries :: Python Modules
Requires-Python: <3.13,>=3.12
Requires-Dist: boto3<2,>=1.35.57
Requires-Dist: pandas<3,>=2.2.3
Requires-Dist: psycopg2-binary<3,>=2.9.10
Requires-Dist: requests<3,>=2.32.3
Requires-Dist: sqlalchemy<3,>=2.0.36
Provides-Extra: all
Requires-Dist: awswrangler<4,>=3.0.0; extra == 'all'
Requires-Dist: opensearch-logger>=1.3.0; extra == 'all'
Provides-Extra: es-logging
Requires-Dist: opensearch-logger>=1.3.0; extra == 'es-logging'
Provides-Extra: parquet
Requires-Dist: awswrangler<4,>=3.0.0; extra == 'parquet'
